ps_constructs/__init__.py
ps_constructs/py.typed
ps_constructs/_jsii/__init__.py
ps_constructs/_jsii/psconstructs@0.1.8.jsii.tgz
psconstructs-0.1.8.dist-info/LICENSE
psconstructs-0.1.8.dist-info/METADATA
psconstructs-0.1.8.dist-info/WHEEL
psconstructs-0.1.8.dist-info/top_level.txt
psconstructs-0.1.8.dist-info/RECORD
